.bumpversion.cfg
.gitignore
CHANGELOG.md
MANIFEST.in
README.rst
justfile
requirements-dev.txt
requirements-flake8.txt
requirements.txt
setup.py
template-version.txt
tox.ini
src/fhs_m3u2strm/__init__.py
src/fhs_m3u2strm/__version__.py
src/fhs_m3u2strm/clean.py
src/fhs_m3u2strm/cli.py
src/fhs_m3u2strm/fhs_m3u2strm.py
src/fhs_m3u2strm/import_m3u.py
src/fhs_m3u2strm/m3u_to_episodes.py
src/fhs_m3u2strm/m3u_to_movies.py
src/fhs_m3u2strm/strm_files.py
src/fhs_m3u2strm/subgroup.py
src/fhs_m3u2strm/vod_groups.py
src/fhs_m3u2strm.egg-info/PKG-INFO
src/fhs_m3u2strm.egg-info/SOURCES.txt
src/fhs_m3u2strm.egg-info/dependency_links.txt
src/fhs_m3u2strm.egg-info/entry_points.txt
src/fhs_m3u2strm.egg-info/requires.txt
src/fhs_m3u2strm.egg-info/top_level.txt
tests/test_sample.py