Metadata-Version: 2.1
Name: fhs-m3u2strm
Version: 1.0.5
Summary: m3u iptv to strm files for iptv2vod services
Home-page: https://github.com/foxhunt72/fhs-m3u2strm
Author: Richard de Vos
Author-email: rdevos72@gmail.com
License: MIT license
Classifier: Development Status :: 5 - Production/Stable
Classifier: Programming Language :: Python
Classifier: Programming Language :: Python :: 3
Classifier: Programming Language :: Python :: 3.6
Classifier: Programming Language :: Python :: 3.7
Classifier: Programming Language :: Python :: 3.8
Classifier: Programming Language :: Python :: 3.9
Classifier: Programming Language :: Python :: 3.10
